[
    {
        "id":6681970,
        "execution_time":0.738,
        "DSSR_iterations":1,
        "utility":-37.54,
        "daily_schedule":[
            {
                "acity":0,
                "facility":0,
                "group":"home",
                "start":0,
                "duration":175,
                "time":175,
                "cum_utility":0.0
            },
            {
                "acity":20,
                "facility":375697,
                "group":"leisure",
                "start":176,
                "duration":4,
                "time":180,
                "cum_utility":-8.64
            },
            {
                "acity":32,
                "facility":377153,
                "group":"shop",
                "start":180,
                "duration":17,
                "time":197,
                "cum_utility":-19.14
            },
            {
                "acity":40,
                "facility":0,
                "group":"home",
                "start":198,
                "duration":20,
                "time":218,
                "cum_utility":-19.04
            },
            {
                "acity":38,
                "facility":377155,
                "group":"education",
                "start":219,
                "duration":11,
                "time":230,
                "cum_utility":-37.64
            },
            {
                "acity":40,
                "facility":0,
                "group":"home",
                "start":231,
                "duration":55,
                "time":286,
                "cum_utility":-37.54
            },
            {
                "acity":41,
                "facility":0,
                "group":"home",
                "start":286,
                "duration":2,
                "time":288,
                "cum_utility":-37.54
            }
        ]
    },
    {
        "id":7072352,
        "execution_time":0.021,
        "DSSR_iterations":1,
        "utility":-8.74,
        "daily_schedule":[
            {
                "acity":0,
                "facility":0,
                "group":"home",
                "start":0,
                "duration":1,
                "time":1,
                "cum_utility":0.0
            },
            {
                "acity":40,
                "facility":0,
                "group":"home",
                "start":1,
                "duration":146,
                "time":147,
                "cum_utility":0.0
            },
            {
                "acity":20,
                "facility":375697,
                "group":"leisure",
                "start":147,
                "duration":2,
                "time":149,
                "cum_utility":-8.74
            },
            {
                "acity":41,
                "facility":0,
                "group":"home",
                "start":149,
                "duration":139,
                "time":288,
                "cum_utility":-8.74
            }
        ]
    },
    {
        "id":6459241,
        "execution_time":0.291,
        "DSSR_iterations":3,
        "utility":-37.54,
        "daily_schedule":[
            {
                "acity":0,
                "facility":0,
                "group":"home",
                "start":0,
                "duration":91,
                "time":91,
                "cum_utility":0.0
            },
            {
                "acity":20,
                "facility":375697,
                "group":"leisure",
                "start":91,
                "duration":6,
                "time":97,
                "cum_utility":-8.74
            },
            {
                "acity":40,
                "facility":0,
                "group":"home",
                "start":97,
                "duration":30,
                "time":127,
                "cum_utility":-8.74
            },
            {
                "acity":38,
                "facility":377155,
                "group":"education",
                "start":128,
                "duration":4,
                "time":132,
                "cum_utility":-27.34
            },
            {
                "acity":40,
                "facility":0,
                "group":"home",
                "start":133,
                "duration":39,
                "time":172,
                "cum_utility":-27.24
            },
            {
                "acity":32,
                "facility":377153,
                "group":"shop",
                "start":173,
                "duration":3,
                "time":176,
                "cum_utility":-37.64
            },
            {
                "acity":40,
                "facility":0,
                "group":"home",
                "start":177,
                "duration":109,
                "time":286,
                "cum_utility":-37.54
            },
            {
                "acity":41,
                "facility":0,
                "group":"home",
                "start":286,
                "duration":2,
                "time":288,
                "cum_utility":-37.54
            }
        ]
    },
    {
        "id":6995165,
        "execution_time":0.715,
        "DSSR_iterations":1,
        "utility":-50.44,
        "daily_schedule":[
            {
                "acity":0,
                "facility":0,
                "group":"home",
                "start":0,
                "duration":1,
                "time":1,
                "cum_utility":0.0
            },
            {
                "acity":40,
                "facility":0,
                "group":"home",
                "start":1,
                "duration":107,
                "time":108,
                "cum_utility":0.0
            },
            {
                "acity":38,
                "facility":377155,
                "group":"education",
                "start":109,
                "duration":34,
                "time":143,
                "cum_utility":-18.6
            },
            {
                "acity":40,
                "facility":0,
                "group":"home",
                "start":144,
                "duration":12,
                "time":156,
                "cum_utility":-18.5
            },
            {
                "acity":39,
                "facility":105296,
                "group":"work",
                "start":158,
                "duration":10,
                "time":168,
                "cum_utility":-31.4
            },
            {
                "acity":40,
                "facility":0,
                "group":"home",
                "start":170,
                "duration":6,
                "time":176,
                "cum_utility":-31.2
            },
            {
                "acity":20,
                "facility":375697,
                "group":"leisure",
                "start":176,
                "duration":24,
                "time":200,
                "cum_utility":-39.94
            },
            {
                "acity":40,
                "facility":0,
                "group":"home",
                "start":200,
                "duration":2,
                "time":202,
                "cum_utility":-39.94
            },
            {
                "acity":32,
                "facility":377153,
                "group":"shop",
                "start":202,
                "duration":3,
                "time":205,
                "cum_utility":-50.44
            },
            {
                "acity":40,
                "facility":0,
                "group":"home",
                "start":205,
                "duration":81,
                "time":286,
                "cum_utility":-50.44
            },
            {
                "acity":41,
                "facility":0,
                "group":"home",
                "start":286,
                "duration":2,
                "time":288,
                "cum_utility":-50.44
            }
        ]
    },
    {
        "id":7003606,
        "execution_time":1.297,
        "DSSR_iterations":1,
        "utility":-35.36,
        "daily_schedule":[
            {
                "acity":0,
                "facility":0,
                "group":"home",
                "start":0,
                "duration":1,
                "time":1,
                "cum_utility":0.0
            },
            {
                "acity":40,
                "facility":0,
                "group":"home",
                "start":1,
                "duration":84,
                "time":85,
                "cum_utility":0.0
            },
            {
                "acity":39,
                "facility":105296,
                "group":"work",
                "start":87,
                "duration":112,
                "time":199,
                "cum_utility":-12.9
            },
            {
                "acity":40,
                "facility":0,
                "group":"home",
                "start":201,
                "duration":18,
                "time":219,
                "cum_utility":-12.7
            },
            {
                "acity":38,
                "facility":377155,
                "group":"education",
                "start":219,
                "duration":22,
                "time":241,
                "cum_utility":-31.4
            },
            {
                "acity":17,
                "facility":377159,
                "group":"leisure",
                "start":241,
                "duration":25,
                "time":266,
                "cum_utility":-35.36
            },
            {
                "acity":40,
                "facility":0,
                "group":"home",
                "start":266,
                "duration":20,
                "time":286,
                "cum_utility":-35.36
            },
            {
                "acity":41,
                "facility":0,
                "group":"home",
                "start":286,
                "duration":2,
                "time":288,
                "cum_utility":-35.36
            }
        ]
    },
    {
        "id":7123852,
        "execution_time":0.41,
        "DSSR_iterations":2,
        "utility":-36.046,
        "daily_schedule":[
            {
                "acity":0,
                "facility":0,
                "group":"home",
                "start":0,
                "duration":96,
                "time":96,
                "cum_utility":0.0
            },
            {
                "acity":20,
                "facility":375697,
                "group":"leisure",
                "start":96,
                "duration":4,
                "time":100,
                "cum_utility":-7.246
            },
            {
                "acity":38,
                "facility":377155,
                "group":"education",
                "start":101,
                "duration":46,
                "time":147,
                "cum_utility":-25.846
            },
            {
                "acity":40,
                "facility":0,
                "group":"home",
                "start":148,
                "duration":73,
                "time":221,
                "cum_utility":-25.746
            },
            {
                "acity":32,
                "facility":377153,
                "group":"shop",
                "start":222,
                "duration":3,
                "time":225,
                "cum_utility":-36.146
            },
            {
                "acity":40,
                "facility":0,
                "group":"home",
                "start":226,
                "duration":60,
                "time":286,
                "cum_utility":-36.046
            },
            {
                "acity":41,
                "facility":0,
                "group":"home",
                "start":286,
                "duration":2,
                "time":288,
                "cum_utility":-36.046
            }
        ]
    },
    {
        "id":6627351,
        "execution_time":0.161,
        "DSSR_iterations":1,
        "utility":-8.54,
        "daily_schedule":[
            {
                "acity":0,
                "facility":0,
                "group":"home",
                "start":0,
                "duration":1,
                "time":1,
                "cum_utility":0.0
            },
            {
                "acity":40,
                "facility":0,
                "group":"home",
                "start":1,
                "duration":227,
                "time":228,
                "cum_utility":0.0
            },
            {
                "acity":20,
                "facility":375697,
                "group":"leisure",
                "start":229,
                "duration":15,
                "time":244,
                "cum_utility":-8.64
            },
            {
                "acity":40,
                "facility":0,
                "group":"home",
                "start":245,
                "duration":41,
                "time":286,
                "cum_utility":-8.54
            },
            {
                "acity":41,
                "facility":0,
                "group":"home",
                "start":286,
                "duration":2,
                "time":288,
                "cum_utility":-8.54
            }
        ]
    },
    {
        "id":7047684,
        "execution_time":0.313,
        "DSSR_iterations":0,
        "utility":-37.64,
        "daily_schedule":[
            {
                "acity":0,
                "facility":0,
                "group":"home",
                "start":0,
                "duration":1,
                "time":1,
                "cum_utility":0.0
            },
            {
                "acity":40,
                "facility":0,
                "group":"home",
                "start":1,
                "duration":100,
                "time":101,
                "cum_utility":0.0
            },
            {
                "acity":20,
                "facility":375697,
                "group":"leisure",
                "start":101,
                "duration":42,
                "time":143,
                "cum_utility":-8.74
            },
            {
                "acity":40,
                "facility":0,
                "group":"home",
                "start":143,
                "duration":42,
                "time":185,
                "cum_utility":-8.74
            },
            {
                "acity":32,
                "facility":377153,
                "group":"shop",
                "start":186,
                "duration":2,
                "time":188,
                "cum_utility":-19.14
            },
            {
                "acity":38,
                "facility":377155,
                "group":"education",
                "start":189,
                "duration":22,
                "time":211,
                "cum_utility":-37.74
            },
            {
                "acity":40,
                "facility":0,
                "group":"home",
                "start":212,
                "duration":74,
                "time":286,
                "cum_utility":-37.64
            },
            {
                "acity":41,
                "facility":0,
                "group":"home",
                "start":286,
                "duration":2,
                "time":288,
                "cum_utility":-37.64
            }
        ]
    },
    {
        "id":6939072,
        "execution_time":21.27,
        "DSSR_iterations":31,
        "utility":-42.644,
        "daily_schedule":[
            {
                "acity":0,
                "facility":0,
                "group":"home",
                "start":0,
                "duration":1,
                "time":1,
                "cum_utility":0.0
            },
            {
                "acity":40,
                "facility":0,
                "group":"home",
                "start":1,
                "duration":147,
                "time":148,
                "cum_utility":0.0
            },
            {
                "acity":38,
                "facility":377155,
                "group":"education",
                "start":149,
                "duration":25,
                "time":174,
                "cum_utility":-18.6
            },
            {
                "acity":40,
                "facility":0,
                "group":"home",
                "start":175,
                "duration":23,
                "time":198,
                "cum_utility":-18.5
            },
            {
                "acity":32,
                "facility":377153,
                "group":"shop",
                "start":199,
                "duration":2,
                "time":201,
                "cum_utility":-28.9
            },
            {
                "acity":20,
                "facility":375697,
                "group":"leisure",
                "start":201,
                "duration":14,
                "time":215,
                "cum_utility":-31.664
            },
            {
                "acity":39,
                "facility":376733,
                "group":"work",
                "start":215,
                "duration":24,
                "time":239,
                "cum_utility":-42.744
            },
            {
                "acity":40,
                "facility":0,
                "group":"home",
                "start":240,
                "duration":46,
                "time":286,
                "cum_utility":-42.644
            },
            {
                "acity":41,
                "facility":0,
                "group":"home",
                "start":286,
                "duration":2,
                "time":288,
                "cum_utility":-42.644
            }
        ]
    },
    {
        "id":7106138,
        "execution_time":0.677,
        "DSSR_iterations":1,
        "utility":-28.925,
        "daily_schedule":[
            {
                "acity":0,
                "facility":0,
                "group":"home",
                "start":0,
                "duration":1,
                "time":1,
                "cum_utility":0.0
            },
            {
                "acity":40,
                "facility":0,
                "group":"home",
                "start":1,
                "duration":70,
                "time":71,
                "cum_utility":0.0
            },
            {
                "acity":20,
                "facility":375697,
                "group":"leisure",
                "start":72,
                "duration":10,
                "time":82,
                "cum_utility":-3.66
            },
            {
                "acity":38,
                "facility":377155,
                "group":"education",
                "start":83,
                "duration":44,
                "time":127,
                "cum_utility":-18.725
            },
            {
                "acity":40,
                "facility":0,
                "group":"home",
                "start":128,
                "duration":6,
                "time":134,
                "cum_utility":-18.625
            },
            {
                "acity":32,
                "facility":377153,
                "group":"shop",
                "start":135,
                "duration":2,
                "time":137,
                "cum_utility":-29.025
            },
            {
                "acity":41,
                "facility":0,
                "group":"home",
                "start":138,
                "duration":150,
                "time":288,
                "cum_utility":-28.925
            }
        ]
    },
    {
        "id":6647609,
        "execution_time":0.447,
        "DSSR_iterations":1,
        "utility":-20.044,
        "daily_schedule":[
            {
                "acity":0,
                "facility":0,
                "group":"home",
                "start":0,
                "duration":1,
                "time":1,
                "cum_utility":0.0
            },
            {
                "acity":40,
                "facility":0,
                "group":"home",
                "start":1,
                "duration":97,
                "time":98,
                "cum_utility":0.0
            },
            {
                "acity":39,
                "facility":368519,
                "group":"work",
                "start":100,
                "duration":26,
                "time":126,
                "cum_utility":-12.9
            },
            {
                "acity":40,
                "facility":0,
                "group":"home",
                "start":128,
                "duration":85,
                "time":213,
                "cum_utility":-12.7
            },
            {
                "acity":20,
                "facility":375697,
                "group":"leisure",
                "start":215,
                "duration":10,
                "time":225,
                "cum_utility":-20.244
            },
            {
                "acity":40,
                "facility":0,
                "group":"home",
                "start":227,
                "duration":59,
                "time":286,
                "cum_utility":-20.044
            },
            {
                "acity":41,
                "facility":0,
                "group":"home",
                "start":286,
                "duration":2,
                "time":288,
                "cum_utility":-20.044
            }
        ]
    },
    {
        "id":7074629,
        "execution_time":0.731,
        "DSSR_iterations":0,
        "utility":-37.64,
        "daily_schedule":[
            {
                "acity":0,
                "facility":0,
                "group":"home",
                "start":0,
                "duration":1,
                "time":1,
                "cum_utility":0.0
            },
            {
                "acity":40,
                "facility":0,
                "group":"home",
                "start":1,
                "duration":139,
                "time":140,
                "cum_utility":0.0
            },
            {
                "acity":32,
                "facility":377153,
                "group":"shop",
                "start":141,
                "duration":20,
                "time":161,
                "cum_utility":-10.4
            },
            {
                "acity":38,
                "facility":377155,
                "group":"education",
                "start":162,
                "duration":42,
                "time":204,
                "cum_utility":-29.0
            },
            {
                "acity":40,
                "facility":0,
                "group":"home",
                "start":205,
                "duration":3,
                "time":208,
                "cum_utility":-28.9
            },
            {
                "acity":20,
                "facility":375697,
                "group":"leisure",
                "start":208,
                "duration":27,
                "time":235,
                "cum_utility":-37.64
            },
            {
                "acity":40,
                "facility":0,
                "group":"home",
                "start":235,
                "duration":51,
                "time":286,
                "cum_utility":-37.64
            },
            {
                "acity":41,
                "facility":0,
                "group":"home",
                "start":286,
                "duration":2,
                "time":288,
                "cum_utility":-37.64
            }
        ]
    },
    {
        "id":6604901,
        "execution_time":0.266,
        "DSSR_iterations":2,
        "utility":-19.24,
        "daily_schedule":[
            {
                "acity":0,
                "facility":0,
                "group":"home",
                "start":0,
                "duration":1,
                "time":1,
                "cum_utility":0.0
            },
            {
                "acity":40,
                "facility":0,
                "group":"home",
                "start":1,
                "duration":188,
                "time":189,
                "cum_utility":0.0
            },
            {
                "acity":32,
                "facility":377153,
                "group":"shop",
                "start":189,
                "duration":5,
                "time":194,
                "cum_utility":-10.5
            },
            {
                "acity":40,
                "facility":0,
                "group":"home",
                "start":194,
                "duration":23,
                "time":217,
                "cum_utility":-10.5
            },
            {
                "acity":20,
                "facility":375697,
                "group":"leisure",
                "start":217,
                "duration":6,
                "time":223,
                "cum_utility":-19.24
            },
            {
                "acity":40,
                "facility":0,
                "group":"home",
                "start":223,
                "duration":63,
                "time":286,
                "cum_utility":-19.24
            },
            {
                "acity":41,
                "facility":0,
                "group":"home",
                "start":286,
                "duration":2,
                "time":288,
                "cum_utility":-19.24
            }
        ]
    },
    {
        "id":6458803,
        "execution_time":0.042,
        "DSSR_iterations":0,
        "utility":-34.75,
        "daily_schedule":[
            {
                "acity":0,
                "facility":0,
                "group":"home",
                "start":0,
                "duration":1,
                "time":1,
                "cum_utility":0.0
            },
            {
                "acity":40,
                "facility":0,
                "group":"home",
                "start":1,
                "duration":112,
                "time":113,
                "cum_utility":0.0
            },
            {
                "acity":20,
                "facility":375697,
                "group":"leisure",
                "start":114,
                "duration":2,
                "time":116,
                "cum_utility":-6.15
            },
            {
                "acity":38,
                "facility":377155,
                "group":"education",
                "start":119,
                "duration":15,
                "time":134,
                "cum_utility":-24.55
            },
            {
                "acity":32,
                "facility":377153,
                "group":"shop",
                "start":135,
                "duration":4,
                "time":139,
                "cum_utility":-34.95
            },
            {
                "acity":40,
                "facility":0,
                "group":"home",
                "start":141,
                "duration":145,
                "time":286,
                "cum_utility":-34.75
            },
            {
                "acity":41,
                "facility":0,
                "group":"home",
                "start":286,
                "duration":2,
                "time":288,
                "cum_utility":-34.75
            }
        ]
    },
    {
        "id":6682096,
        "execution_time":0.365,
        "DSSR_iterations":1,
        "utility":-19.24,
        "daily_schedule":[
            {
                "acity":0,
                "facility":0,
                "group":"home",
                "start":0,
                "duration":141,
                "time":141,
                "cum_utility":0.0
            },
            {
                "acity":20,
                "facility":375697,
                "group":"leisure",
                "start":141,
                "duration":15,
                "time":156,
                "cum_utility":-8.74
            },
            {
                "acity":40,
                "facility":0,
                "group":"home",
                "start":156,
                "duration":60,
                "time":216,
                "cum_utility":-8.74
            },
            {
                "acity":32,
                "facility":377153,
                "group":"shop",
                "start":216,
                "duration":22,
                "time":238,
                "cum_utility":-19.24
            },
            {
                "acity":40,
                "facility":0,
                "group":"home",
                "start":238,
                "duration":48,
                "time":286,
                "cum_utility":-19.24
            },
            {
                "acity":41,
                "facility":0,
                "group":"home",
                "start":286,
                "duration":2,
                "time":288,
                "cum_utility":-19.24
            }
        ]
    },
    {
        "id":6459005,
        "execution_time":0.682,
        "DSSR_iterations":2,
        "utility":-50.84,
        "daily_schedule":[
            {
                "acity":0,
                "facility":0,
                "group":"home",
                "start":0,
                "duration":1,
                "time":1,
                "cum_utility":0.0
            },
            {
                "acity":40,
                "facility":0,
                "group":"home",
                "start":1,
                "duration":115,
                "time":116,
                "cum_utility":0.0
            },
            {
                "acity":32,
                "facility":377153,
                "group":"shop",
                "start":116,
                "duration":3,
                "time":119,
                "cum_utility":-10.5
            },
            {
                "acity":40,
                "facility":0,
                "group":"home",
                "start":119,
                "duration":44,
                "time":163,
                "cum_utility":-10.5
            },
            {
                "acity":39,
                "facility":92659,
                "group":"work",
                "start":163,
                "duration":34,
                "time":197,
                "cum_utility":-23.6
            },
            {
                "acity":40,
                "facility":0,
                "group":"home",
                "start":197,
                "duration":24,
                "time":221,
                "cum_utility":-23.6
            },
            {
                "acity":38,
                "facility":377155,
                "group":"education",
                "start":222,
                "duration":13,
                "time":235,
                "cum_utility":-42.2
            },
            {
                "acity":20,
                "facility":375697,
                "group":"leisure",
                "start":236,
                "duration":14,
                "time":250,
                "cum_utility":-50.84
            },
            {
                "acity":40,
                "facility":0,
                "group":"home",
                "start":250,
                "duration":36,
                "time":286,
                "cum_utility":-50.84
            },
            {
                "acity":41,
                "facility":0,
                "group":"home",
                "start":286,
                "duration":2,
                "time":288,
                "cum_utility":-50.84
            }
        ]
    },
    {
        "id":6986382,
        "execution_time":0.771,
        "DSSR_iterations":2,
        "utility":-37.34,
        "daily_schedule":[
            {
                "acity":0,
                "facility":0,
                "group":"home",
                "start":0,
                "duration":1,
                "time":1,
                "cum_utility":0.0
            },
            {
                "acity":40,
                "facility":0,
                "group":"home",
                "start":1,
                "duration":96,
                "time":97,
                "cum_utility":0.0
            },
            {
                "acity":38,
                "facility":377155,
                "group":"education",
                "start":98,
                "duration":40,
                "time":138,
                "cum_utility":-18.6
            },
            {
                "acity":40,
                "facility":0,
                "group":"home",
                "start":139,
                "duration":15,
                "time":154,
                "cum_utility":-18.5
            },
            {
                "acity":32,
                "facility":377153,
                "group":"shop",
                "start":155,
                "duration":3,
                "time":158,
                "cum_utility":-28.9
            },
            {
                "acity":40,
                "facility":0,
                "group":"home",
                "start":159,
                "duration":79,
                "time":238,
                "cum_utility":-28.8
            },
            {
                "acity":20,
                "facility":375697,
                "group":"leisure",
                "start":239,
                "duration":8,
                "time":247,
                "cum_utility":-37.44
            },
            {
                "acity":40,
                "facility":0,
                "group":"home",
                "start":248,
                "duration":38,
                "time":286,
                "cum_utility":-37.34
            },
            {
                "acity":41,
                "facility":0,
                "group":"home",
                "start":286,
                "duration":2,
                "time":288,
                "cum_utility":-37.34
            }
        ]
    },
    {
        "id":6987214,
        "execution_time":1.842,
        "DSSR_iterations":14,
        "utility":-34.752,
        "daily_schedule":[
            {
                "acity":0,
                "facility":0,
                "group":"home",
                "start":0,
                "duration":1,
                "time":1,
                "cum_utility":0.0
            },
            {
                "acity":40,
                "facility":0,
                "group":"home",
                "start":1,
                "duration":160,
                "time":161,
                "cum_utility":0.0
            },
            {
                "acity":32,
                "facility":377153,
                "group":"shop",
                "start":161,
                "duration":3,
                "time":164,
                "cum_utility":-10.5
            },
            {
                "acity":40,
                "facility":0,
                "group":"home",
                "start":164,
                "duration":4,
                "time":168,
                "cum_utility":-10.5
            },
            {
                "acity":20,
                "facility":375697,
                "group":"leisure",
                "start":168,
                "duration":14,
                "time":182,
                "cum_utility":-16.252
            },
            {
                "acity":40,
                "facility":0,
                "group":"home",
                "start":182,
                "duration":43,
                "time":225,
                "cum_utility":-16.252
            },
            {
                "acity":38,
                "facility":377155,
                "group":"education",
                "start":226,
                "duration":2,
                "time":228,
                "cum_utility":-34.852
            },
            {
                "acity":41,
                "facility":0,
                "group":"home",
                "start":229,
                "duration":59,
                "time":288,
                "cum_utility":-34.752
            }
        ]
    },
    {
        "id":6459019,
        "execution_time":0.841,
        "DSSR_iterations":8,
        "utility":-24.75,
        "daily_schedule":[
            {
                "acity":0,
                "facility":0,
                "group":"home",
                "start":0,
                "duration":126,
                "time":126,
                "cum_utility":0.0
            },
            {
                "acity":40,
                "facility":0,
                "group":"home",
                "start":126,
                "duration":62,
                "time":188,
                "cum_utility":0.0
            },
            {
                "acity":38,
                "facility":377155,
                "group":"education",
                "start":189,
                "duration":7,
                "time":196,
                "cum_utility":-18.6
            },
            {
                "acity":20,
                "facility":375697,
                "group":"leisure",
                "start":197,
                "duration":7,
                "time":204,
                "cum_utility":-24.75
            },
            {
                "acity":40,
                "facility":0,
                "group":"home",
                "start":204,
                "duration":82,
                "time":286,
                "cum_utility":-24.75
            },
            {
                "acity":41,
                "facility":0,
                "group":"home",
                "start":286,
                "duration":2,
                "time":288,
                "cum_utility":-24.75
            }
        ]
    },
    {
        "id":6682328,
        "execution_time":1.535,
        "DSSR_iterations":13,
        "utility":-34.552,
        "daily_schedule":[
            {
                "acity":0,
                "facility":0,
                "group":"home",
                "start":0,
                "duration":1,
                "time":1,
                "cum_utility":0.0
            },
            {
                "acity":40,
                "facility":0,
                "group":"home",
                "start":1,
                "duration":98,
                "time":99,
                "cum_utility":0.0
            },
            {
                "acity":20,
                "facility":375697,
                "group":"leisure",
                "start":99,
                "duration":14,
                "time":113,
                "cum_utility":-5.752
            },
            {
                "acity":32,
                "facility":377153,
                "group":"shop",
                "start":114,
                "duration":2,
                "time":116,
                "cum_utility":-16.152
            },
            {
                "acity":40,
                "facility":0,
                "group":"home",
                "start":117,
                "duration":66,
                "time":183,
                "cum_utility":-16.052
            },
            {
                "acity":38,
                "facility":377155,
                "group":"education",
                "start":184,
                "duration":13,
                "time":197,
                "cum_utility":-34.652
            },
            {
                "acity":40,
                "facility":0,
                "group":"home",
                "start":198,
                "duration":88,
                "time":286,
                "cum_utility":-34.552
            },
            {
                "acity":41,
                "facility":0,
                "group":"home",
                "start":286,
                "duration":2,
                "time":288,
                "cum_utility":-34.552
            }
        ]
    },
    {
        "id":6681925,
        "execution_time":0.599,
        "DSSR_iterations":2,
        "utility":-27.44,
        "daily_schedule":[
            {
                "acity":0,
                "facility":0,
                "group":"home",
                "start":0,
                "duration":210,
                "time":210,
                "cum_utility":0.0
            },
            {
                "acity":20,
                "facility":375697,
                "group":"leisure",
                "start":210,
                "duration":10,
                "time":220,
                "cum_utility":-8.74
            },
            {
                "acity":38,
                "facility":377155,
                "group":"education",
                "start":220,
                "duration":22,
                "time":242,
                "cum_utility":-27.44
            },
            {
                "acity":40,
                "facility":0,
                "group":"home",
                "start":242,
                "duration":44,
                "time":286,
                "cum_utility":-27.44
            },
            {
                "acity":41,
                "facility":0,
                "group":"home",
                "start":286,
                "duration":2,
                "time":288,
                "cum_utility":-27.44
            }
        ]
    },
    {
        "id":6459353,
        "execution_time":0.348,
        "DSSR_iterations":1,
        "utility":-37.14,
        "daily_schedule":[
            {
                "acity":0,
                "facility":0,
                "group":"home",
                "start":0,
                "duration":1,
                "time":1,
                "cum_utility":0.0
            },
            {
                "acity":40,
                "facility":0,
                "group":"home",
                "start":1,
                "duration":140,
                "time":141,
                "cum_utility":0.0
            },
            {
                "acity":20,
                "facility":375697,
                "group":"leisure",
                "start":142,
                "duration":18,
                "time":160,
                "cum_utility":-8.64
            },
            {
                "acity":40,
                "facility":0,
                "group":"home",
                "start":161,
                "duration":11,
                "time":172,
                "cum_utility":-8.54
            },
            {
                "acity":32,
                "facility":377153,
                "group":"shop",
                "start":174,
                "duration":3,
                "time":177,
                "cum_utility":-18.84
            },
            {
                "acity":40,
                "facility":0,
                "group":"home",
                "start":179,
                "duration":26,
                "time":205,
                "cum_utility":-18.64
            },
            {
                "acity":38,
                "facility":377155,
                "group":"education",
                "start":206,
                "duration":18,
                "time":224,
                "cum_utility":-37.24
            },
            {
                "acity":40,
                "facility":0,
                "group":"home",
                "start":225,
                "duration":61,
                "time":286,
                "cum_utility":-37.14
            },
            {
                "acity":41,
                "facility":0,
                "group":"home",
                "start":286,
                "duration":2,
                "time":288,
                "cum_utility":-37.14
            }
        ]
    },
    {
        "id":6459083,
        "execution_time":0.148,
        "DSSR_iterations":1,
        "utility":-36.54,
        "daily_schedule":[
            {
                "acity":0,
                "facility":0,
                "group":"home",
                "start":0,
                "duration":1,
                "time":1,
                "cum_utility":0.0
            },
            {
                "acity":40,
                "facility":0,
                "group":"home",
                "start":1,
                "duration":121,
                "time":122,
                "cum_utility":0.0
            },
            {
                "acity":20,
                "facility":375697,
                "group":"leisure",
                "start":123,
                "duration":3,
                "time":126,
                "cum_utility":-8.64
            },
            {
                "acity":40,
                "facility":0,
                "group":"home",
                "start":127,
                "duration":1,
                "time":128,
                "cum_utility":-8.14
            },
            {
                "acity":38,
                "facility":377155,
                "group":"education",
                "start":129,
                "duration":13,
                "time":142,
                "cum_utility":-26.74
            },
            {
                "acity":40,
                "facility":0,
                "group":"home",
                "start":143,
                "duration":19,
                "time":162,
                "cum_utility":-26.64
            },
            {
                "acity":32,
                "facility":377153,
                "group":"shop",
                "start":165,
                "duration":3,
                "time":168,
                "cum_utility":-36.84
            },
            {
                "acity":40,
                "facility":0,
                "group":"home",
                "start":171,
                "duration":115,
                "time":286,
                "cum_utility":-36.54
            },
            {
                "acity":41,
                "facility":0,
                "group":"home",
                "start":286,
                "duration":2,
                "time":288,
                "cum_utility":-36.54
            }
        ]
    },
    {
        "id":6459226,
        "execution_time":0.154,
        "DSSR_iterations":1,
        "utility":-33.656,
        "daily_schedule":[
            {
                "acity":0,
                "facility":0,
                "group":"home",
                "start":0,
                "duration":1,
                "time":1,
                "cum_utility":0.0
            },
            {
                "acity":40,
                "facility":0,
                "group":"home",
                "start":1,
                "duration":110,
                "time":111,
                "cum_utility":0.0
            },
            {
                "acity":32,
                "facility":377153,
                "group":"shop",
                "start":112,
                "duration":2,
                "time":114,
                "cum_utility":-10.4
            },
            {
                "acity":38,
                "facility":377155,
                "group":"education",
                "start":115,
                "duration":13,
                "time":128,
                "cum_utility":-29.0
            },
            {
                "acity":40,
                "facility":0,
                "group":"home",
                "start":129,
                "duration":25,
                "time":154,
                "cum_utility":-28.9
            },
            {
                "acity":20,
                "facility":375697,
                "group":"leisure",
                "start":154,
                "duration":9,
                "time":163,
                "cum_utility":-33.656
            },
            {
                "acity":40,
                "facility":0,
                "group":"home",
                "start":163,
                "duration":123,
                "time":286,
                "cum_utility":-33.656
            },
            {
                "acity":41,
                "facility":0,
                "group":"home",
                "start":286,
                "duration":2,
                "time":288,
                "cum_utility":-33.656
            }
        ]
    },
    {
        "id":6458884,
        "execution_time":0.239,
        "DSSR_iterations":1,
        "utility":-25.248,
        "daily_schedule":[
            {
                "acity":0,
                "facility":0,
                "group":"home",
                "start":0,
                "duration":1,
                "time":1,
                "cum_utility":0.0
            },
            {
                "acity":40,
                "facility":0,
                "group":"home",
                "start":1,
                "duration":203,
                "time":204,
                "cum_utility":0.0
            },
            {
                "acity":38,
                "facility":377155,
                "group":"education",
                "start":204,
                "duration":10,
                "time":214,
                "cum_utility":-18.7
            },
            {
                "acity":40,
                "facility":0,
                "group":"home",
                "start":214,
                "duration":4,
                "time":218,
                "cum_utility":-18.7
            },
            {
                "acity":20,
                "facility":375697,
                "group":"leisure",
                "start":219,
                "duration":7,
                "time":226,
                "cum_utility":-25.348
            },
            {
                "acity":40,
                "facility":0,
                "group":"home",
                "start":227,
                "duration":59,
                "time":286,
                "cum_utility":-25.248
            },
            {
                "acity":41,
                "facility":0,
                "group":"home",
                "start":286,
                "duration":2,
                "time":288,
                "cum_utility":-25.248
            }
        ]
    },
    {
        "id":6681562,
        "execution_time":0.326,
        "DSSR_iterations":1,
        "utility":-32.854,
        "daily_schedule":[
            {
                "acity":0,
                "facility":0,
                "group":"home",
                "start":0,
                "duration":1,
                "time":1,
                "cum_utility":0.0
            },
            {
                "acity":40,
                "facility":0,
                "group":"home",
                "start":1,
                "duration":97,
                "time":98,
                "cum_utility":0.0
            },
            {
                "acity":32,
                "facility":377153,
                "group":"shop",
                "start":102,
                "duration":7,
                "time":109,
                "cum_utility":-10.1
            },
            {
                "acity":40,
                "facility":0,
                "group":"home",
                "start":113,
                "duration":7,
                "time":120,
                "cum_utility":-9.7
            },
            {
                "acity":20,
                "facility":375697,
                "group":"leisure",
                "start":121,
                "duration":8,
                "time":129,
                "cum_utility":-14.854
            },
            {
                "acity":40,
                "facility":0,
                "group":"home",
                "start":130,
                "duration":71,
                "time":201,
                "cum_utility":-14.754
            },
            {
                "acity":38,
                "facility":377155,
                "group":"education",
                "start":204,
                "duration":18,
                "time":222,
                "cum_utility":-33.154
            },
            {
                "acity":40,
                "facility":0,
                "group":"home",
                "start":225,
                "duration":61,
                "time":286,
                "cum_utility":-32.854
            },
            {
                "acity":41,
                "facility":0,
                "group":"home",
                "start":286,
                "duration":2,
                "time":288,
                "cum_utility":-32.854
            }
        ]
    },
    {
        "id":6981972,
        "execution_time":0.331,
        "DSSR_iterations":1,
        "utility":-31.364,
        "daily_schedule":[
            {
                "acity":0,
                "facility":0,
                "group":"home",
                "start":0,
                "duration":1,
                "time":1,
                "cum_utility":0.0
            },
            {
                "acity":40,
                "facility":0,
                "group":"home",
                "start":1,
                "duration":109,
                "time":110,
                "cum_utility":0.0
            },
            {
                "acity":32,
                "facility":377153,
                "group":"shop",
                "start":111,
                "duration":11,
                "time":122,
                "cum_utility":-10.4
            },
            {
                "acity":40,
                "facility":0,
                "group":"home",
                "start":123,
                "duration":25,
                "time":148,
                "cum_utility":-10.3
            },
            {
                "acity":20,
                "facility":375697,
                "group":"leisure",
                "start":149,
                "duration":3,
                "time":152,
                "cum_utility":-12.964
            },
            {
                "acity":40,
                "facility":0,
                "group":"home",
                "start":153,
                "duration":4,
                "time":157,
                "cum_utility":-12.864
            },
            {
                "acity":38,
                "facility":377155,
                "group":"education",
                "start":158,
                "duration":41,
                "time":199,
                "cum_utility":-31.464
            },
            {
                "acity":40,
                "facility":0,
                "group":"home",
                "start":200,
                "duration":86,
                "time":286,
                "cum_utility":-31.364
            },
            {
                "acity":41,
                "facility":0,
                "group":"home",
                "start":286,
                "duration":2,
                "time":288,
                "cum_utility":-31.364
            }
        ]
    },
    {
        "id":6980079,
        "execution_time":0.113,
        "DSSR_iterations":0,
        "utility":-29.572,
        "daily_schedule":[
            {
                "acity":0,
                "facility":0,
                "group":"home",
                "start":0,
                "duration":1,
                "time":1,
                "cum_utility":0.0
            },
            {
                "acity":40,
                "facility":0,
                "group":"home",
                "start":1,
                "duration":89,
                "time":90,
                "cum_utility":0.0
            },
            {
                "acity":20,
                "facility":375697,
                "group":"leisure",
                "start":90,
                "duration":22,
                "time":112,
                "cum_utility":-0.772
            },
            {
                "acity":38,
                "facility":377155,
                "group":"education",
                "start":113,
                "duration":10,
                "time":123,
                "cum_utility":-19.372
            },
            {
                "acity":40,
                "facility":0,
                "group":"home",
                "start":124,
                "duration":75,
                "time":199,
                "cum_utility":-19.272
            },
            {
                "acity":32,
                "facility":377153,
                "group":"shop",
                "start":200,
                "duration":6,
                "time":206,
                "cum_utility":-29.672
            },
            {
                "acity":40,
                "facility":0,
                "group":"home",
                "start":207,
                "duration":79,
                "time":286,
                "cum_utility":-29.572
            },
            {
                "acity":41,
                "facility":0,
                "group":"home",
                "start":286,
                "duration":2,
                "time":288,
                "cum_utility":-29.572
            }
        ]
    },
    {
        "id":6326697,
        "execution_time":0.44,
        "DSSR_iterations":2,
        "utility":-19.24,
        "daily_schedule":[
            {
                "acity":0,
                "facility":0,
                "group":"home",
                "start":0,
                "duration":1,
                "time":1,
                "cum_utility":0.0
            },
            {
                "acity":40,
                "facility":0,
                "group":"home",
                "start":1,
                "duration":102,
                "time":103,
                "cum_utility":0.0
            },
            {
                "acity":32,
                "facility":377153,
                "group":"shop",
                "start":103,
                "duration":3,
                "time":106,
                "cum_utility":-10.5
            },
            {
                "acity":40,
                "facility":0,
                "group":"home",
                "start":106,
                "duration":65,
                "time":171,
                "cum_utility":-10.5
            },
            {
                "acity":20,
                "facility":375697,
                "group":"leisure",
                "start":171,
                "duration":20,
                "time":191,
                "cum_utility":-19.24
            },
            {
                "acity":40,
                "facility":0,
                "group":"home",
                "start":191,
                "duration":95,
                "time":286,
                "cum_utility":-19.24
            },
            {
                "acity":41,
                "facility":0,
                "group":"home",
                "start":286,
                "duration":2,
                "time":288,
                "cum_utility":-19.24
            }
        ]
    },
    {
        "id":6326572,
        "execution_time":0.341,
        "DSSR_iterations":1,
        "utility":-36.046,
        "daily_schedule":[
            {
                "acity":0,
                "facility":0,
                "group":"home",
                "start":0,
                "duration":1,
                "time":1,
                "cum_utility":0.0
            },
            {
                "acity":40,
                "facility":0,
                "group":"home",
                "start":1,
                "duration":113,
                "time":114,
                "cum_utility":0.0
            },
            {
                "acity":32,
                "facility":377153,
                "group":"shop",
                "start":115,
                "duration":36,
                "time":151,
                "cum_utility":-10.4
            },
            {
                "acity":20,
                "facility":375697,
                "group":"leisure",
                "start":152,
                "duration":2,
                "time":154,
                "cum_utility":-17.546
            },
            {
                "acity":40,
                "facility":0,
                "group":"home",
                "start":154,
                "duration":57,
                "time":211,
                "cum_utility":-17.546
            },
            {
                "acity":38,
                "facility":377155,
                "group":"education",
                "start":212,
                "duration":22,
                "time":234,
                "cum_utility":-36.146
            },
            {
                "acity":40,
                "facility":0,
                "group":"home",
                "start":235,
                "duration":51,
                "time":286,
                "cum_utility":-36.046
            },
            {
                "acity":41,
                "facility":0,
                "group":"home",
                "start":286,
                "duration":2,
                "time":288,
                "cum_utility":-36.046
            }
        ]
    },
    {
        "id":6682531,
        "execution_time":0.706,
        "DSSR_iterations":1,
        "utility":-28.06,
        "daily_schedule":[
            {
                "acity":0,
                "facility":0,
                "group":"home",
                "start":0,
                "duration":1,
                "time":1,
                "cum_utility":0.0
            },
            {
                "acity":40,
                "facility":0,
                "group":"home",
                "start":1,
                "duration":118,
                "time":119,
                "cum_utility":0.0
            },
            {
                "acity":20,
                "facility":375697,
                "group":"leisure",
                "start":122,
                "duration":13,
                "time":135,
                "cum_utility":-8.44
            },
            {
                "acity":40,
                "facility":0,
                "group":"home",
                "start":138,
                "duration":11,
                "time":149,
                "cum_utility":-8.14
            },
            {
                "acity":38,
                "facility":377155,
                "group":"education",
                "start":150,
                "duration":56,
                "time":206,
                "cum_utility":-26.74
            },
            {
                "acity":32,
                "facility":377153,
                "group":"shop",
                "start":209,
                "duration":2,
                "time":211,
                "cum_utility":-28.36
            },
            {
                "acity":40,
                "facility":0,
                "group":"home",
                "start":214,
                "duration":72,
                "time":286,
                "cum_utility":-28.06
            },
            {
                "acity":41,
                "facility":0,
                "group":"home",
                "start":286,
                "duration":2,
                "time":288,
                "cum_utility":-28.06
            }
        ]
    },
    {
        "id":7005010,
        "execution_time":0.574,
        "DSSR_iterations":1,
        "utility":-28.2,
        "daily_schedule":[
            {
                "acity":0,
                "facility":0,
                "group":"home",
                "start":0,
                "duration":1,
                "time":1,
                "cum_utility":0.0
            },
            {
                "acity":40,
                "facility":0,
                "group":"home",
                "start":1,
                "duration":132,
                "time":133,
                "cum_utility":0.0
            },
            {
                "acity":32,
                "facility":377153,
                "group":"shop",
                "start":135,
                "duration":3,
                "time":138,
                "cum_utility":-10.3
            },
            {
                "acity":40,
                "facility":0,
                "group":"home",
                "start":140,
                "duration":18,
                "time":158,
                "cum_utility":-10.1
            },
            {
                "acity":38,
                "facility":377155,
                "group":"education",
                "start":161,
                "duration":86,
                "time":247,
                "cum_utility":-28.5
            },
            {
                "acity":40,
                "facility":0,
                "group":"home",
                "start":250,
                "duration":36,
                "time":286,
                "cum_utility":-28.2
            },
            {
                "acity":41,
                "facility":0,
                "group":"home",
                "start":286,
                "duration":2,
                "time":288,
                "cum_utility":-28.2
            }
        ]
    },
    {
        "id":6682074,
        "execution_time":0.435,
        "DSSR_iterations":0,
        "utility":-36.74,
        "daily_schedule":[
            {
                "acity":0,
                "facility":0,
                "group":"home",
                "start":0,
                "duration":1,
                "time":1,
                "cum_utility":0.0
            },
            {
                "acity":40,
                "facility":0,
                "group":"home",
                "start":1,
                "duration":158,
                "time":159,
                "cum_utility":0.0
            },
            {
                "acity":32,
                "facility":377153,
                "group":"shop",
                "start":161,
                "duration":11,
                "time":172,
                "cum_utility":-10.3
            },
            {
                "acity":40,
                "facility":0,
                "group":"home",
                "start":174,
                "duration":35,
                "time":209,
                "cum_utility":-10.1
            },
            {
                "acity":38,
                "facility":377155,
                "group":"education",
                "start":212,
                "duration":11,
                "time":223,
                "cum_utility":-28.5
            },
            {
                "acity":40,
                "facility":0,
                "group":"home",
                "start":226,
                "duration":22,
                "time":248,
                "cum_utility":-28.2
            },
            {
                "acity":20,
                "facility":375697,
                "group":"leisure",
                "start":249,
                "duration":35,
                "time":284,
                "cum_utility":-36.84
            },
            {
                "acity":40,
                "facility":0,
                "group":"home",
                "start":285,
                "duration":1,
                "time":286,
                "cum_utility":-36.74
            },
            {
                "acity":41,
                "facility":0,
                "group":"home",
                "start":286,
                "duration":2,
                "time":288,
                "cum_utility":-36.74
            }
        ]
    },
    {
        "id":6630966,
        "execution_time":2.737,
        "DSSR_iterations":32,
        "utility":-46.656,
        "daily_schedule":[
            {
                "acity":0,
                "facility":0,
                "group":"home",
                "start":0,
                "duration":1,
                "time":1,
                "cum_utility":0.0
            },
            {
                "acity":40,
                "facility":0,
                "group":"home",
                "start":1,
                "duration":126,
                "time":127,
                "cum_utility":0.0
            },
            {
                "acity":38,
                "facility":377155,
                "group":"education",
                "start":128,
                "duration":4,
                "time":132,
                "cum_utility":-18.6
            },
            {
                "acity":40,
                "facility":0,
                "group":"home",
                "start":133,
                "duration":28,
                "time":161,
                "cum_utility":-18.5
            },
            {
                "acity":20,
                "facility":375697,
                "group":"leisure",
                "start":162,
                "duration":2,
                "time":164,
                "cum_utility":-23.156
            },
            {
                "acity":32,
                "facility":377153,
                "group":"shop",
                "start":164,
                "duration":8,
                "time":172,
                "cum_utility":-33.656
            },
            {
                "acity":39,
                "facility":298968,
                "group":"work",
                "start":172,
                "duration":4,
                "time":176,
                "cum_utility":-46.756
            },
            {
                "acity":40,
                "facility":0,
                "group":"home",
                "start":177,
                "duration":109,
                "time":286,
                "cum_utility":-46.656
            },
            {
                "acity":41,
                "facility":0,
                "group":"home",
                "start":286,
                "duration":2,
                "time":288,
                "cum_utility":-46.656
            }
        ]
    },
    {
        "id":7088770,
        "execution_time":0.112,
        "DSSR_iterations":2,
        "utility":-18.84,
        "daily_schedule":[
            {
                "acity":0,
                "facility":0,
                "group":"home",
                "start":0,
                "duration":1,
                "time":1,
                "cum_utility":0.0
            },
            {
                "acity":40,
                "facility":0,
                "group":"home",
                "start":1,
                "duration":103,
                "time":104,
                "cum_utility":0.0
            },
            {
                "acity":32,
                "facility":377153,
                "group":"shop",
                "start":105,
                "duration":3,
                "time":108,
                "cum_utility":-10.4
            },
            {
                "acity":40,
                "facility":0,
                "group":"home",
                "start":109,
                "duration":79,
                "time":188,
                "cum_utility":-10.3
            },
            {
                "acity":20,
                "facility":375697,
                "group":"leisure",
                "start":189,
                "duration":3,
                "time":192,
                "cum_utility":-18.94
            },
            {
                "acity":40,
                "facility":0,
                "group":"home",
                "start":193,
                "duration":93,
                "time":286,
                "cum_utility":-18.84
            },
            {
                "acity":41,
                "facility":0,
                "group":"home",
                "start":286,
                "duration":2,
                "time":288,
                "cum_utility":-18.84
            }
        ]
    },
    {
        "id":6458818,
        "execution_time":0.338,
        "DSSR_iterations":1,
        "utility":-36.952,
        "daily_schedule":[
            {
                "acity":0,
                "facility":0,
                "group":"home",
                "start":0,
                "duration":1,
                "time":1,
                "cum_utility":0.0
            },
            {
                "acity":40,
                "facility":0,
                "group":"home",
                "start":1,
                "duration":73,
                "time":74,
                "cum_utility":0.0
            },
            {
                "acity":39,
                "facility":126978,
                "group":"work",
                "start":75,
                "duration":69,
                "time":144,
                "cum_utility":-13.0
            },
            {
                "acity":40,
                "facility":0,
                "group":"home",
                "start":145,
                "duration":32,
                "time":177,
                "cum_utility":-12.9
            },
            {
                "acity":20,
                "facility":375697,
                "group":"leisure",
                "start":178,
                "duration":9,
                "time":187,
                "cum_utility":-18.552
            },
            {
                "acity":40,
                "facility":0,
                "group":"home",
                "start":188,
                "duration":29,
                "time":217,
                "cum_utility":-18.452
            },
            {
                "acity":38,
                "facility":377155,
                "group":"education",
                "start":218,
                "duration":12,
                "time":230,
                "cum_utility":-37.052
            },
            {
                "acity":40,
                "facility":0,
                "group":"home",
                "start":231,
                "duration":55,
                "time":286,
                "cum_utility":-36.952
            },
            {
                "acity":41,
                "facility":0,
                "group":"home",
                "start":286,
                "duration":2,
                "time":288,
                "cum_utility":-36.952
            }
        ]
    },
    {
        "id":6643292,
        "execution_time":0.661,
        "DSSR_iterations":1,
        "utility":-24.47,
        "daily_schedule":[
            {
                "acity":0,
                "facility":0,
                "group":"home",
                "start":0,
                "duration":1,
                "time":1,
                "cum_utility":0.0
            },
            {
                "acity":40,
                "facility":0,
                "group":"home",
                "start":1,
                "duration":127,
                "time":128,
                "cum_utility":0.0
            },
            {
                "acity":20,
                "facility":375697,
                "group":"leisure",
                "start":129,
                "duration":8,
                "time":137,
                "cum_utility":-1.17
            },
            {
                "acity":32,
                "facility":377153,
                "group":"shop",
                "start":137,
                "duration":22,
                "time":159,
                "cum_utility":-11.67
            },
            {
                "acity":40,
                "facility":0,
                "group":"home",
                "start":160,
                "duration":51,
                "time":211,
                "cum_utility":-11.57
            },
            {
                "acity":39,
                "facility":128376,
                "group":"work",
                "start":212,
                "duration":42,
                "time":254,
                "cum_utility":-24.57
            },
            {
                "acity":40,
                "facility":0,
                "group":"home",
                "start":255,
                "duration":31,
                "time":286,
                "cum_utility":-24.47
            },
            {
                "acity":41,
                "facility":0,
                "group":"home",
                "start":286,
                "duration":2,
                "time":288,
                "cum_utility":-24.47
            }
        ]
    },
    {
        "id":6682710,
        "execution_time":0.374,
        "DSSR_iterations":1,
        "utility":-34.525,
        "daily_schedule":[
            {
                "acity":0,
                "facility":0,
                "group":"home",
                "start":0,
                "duration":1,
                "time":1,
                "cum_utility":0.0
            },
            {
                "acity":40,
                "facility":0,
                "group":"home",
                "start":1,
                "duration":92,
                "time":93,
                "cum_utility":0.0
            },
            {
                "acity":32,
                "facility":377153,
                "group":"shop",
                "start":93,
                "duration":3,
                "time":96,
                "cum_utility":-10.5
            },
            {
                "acity":40,
                "facility":0,
                "group":"home",
                "start":96,
                "duration":93,
                "time":189,
                "cum_utility":-7.085
            },
            {
                "acity":20,
                "facility":375697,
                "group":"leisure",
                "start":189,
                "duration":3,
                "time":192,
                "cum_utility":-15.825
            },
            {
                "acity":40,
                "facility":0,
                "group":"home",
                "start":192,
                "duration":27,
                "time":219,
                "cum_utility":-15.825
            },
            {
                "acity":38,
                "facility":377155,
                "group":"education",
                "start":219,
                "duration":34,
                "time":253,
                "cum_utility":-34.525
            },
            {
                "acity":40,
                "facility":0,
                "group":"home",
                "start":253,
                "duration":33,
                "time":286,
                "cum_utility":-34.525
            },
            {
                "acity":41,
                "facility":0,
                "group":"home",
                "start":286,
                "duration":2,
                "time":288,
                "cum_utility":-34.525
            }
        ]
    },
    {
        "id":6954665,
        "execution_time":0.262,
        "DSSR_iterations":2,
        "utility":-27.24,
        "daily_schedule":[
            {
                "acity":0,
                "facility":0,
                "group":"home",
                "start":0,
                "duration":1,
                "time":1,
                "cum_utility":0.0
            },
            {
                "acity":40,
                "facility":0,
                "group":"home",
                "start":1,
                "duration":97,
                "time":98,
                "cum_utility":0.0
            },
            {
                "acity":38,
                "facility":377155,
                "group":"education",
                "start":99,
                "duration":57,
                "time":156,
                "cum_utility":-18.6
            },
            {
                "acity":40,
                "facility":0,
                "group":"home",
                "start":157,
                "duration":55,
                "time":212,
                "cum_utility":-18.5
            },
            {
                "acity":20,
                "facility":375697,
                "group":"leisure",
                "start":212,
                "duration":3,
                "time":215,
                "cum_utility":-27.24
            },
            {
                "acity":40,
                "facility":0,
                "group":"home",
                "start":215,
                "duration":71,
                "time":286,
                "cum_utility":-27.24
            },
            {
                "acity":41,
                "facility":0,
                "group":"home",
                "start":286,
                "duration":2,
                "time":288,
                "cum_utility":-27.24
            }
        ]
    },
    {
        "id":6681845,
        "execution_time":0.238,
        "DSSR_iterations":1,
        "utility":-28.8,
        "daily_schedule":[
            {
                "acity":0,
                "facility":0,
                "group":"home",
                "start":0,
                "duration":1,
                "time":1,
                "cum_utility":0.0
            },
            {
                "acity":40,
                "facility":0,
                "group":"home",
                "start":1,
                "duration":97,
                "time":98,
                "cum_utility":0.0
            },
            {
                "acity":38,
                "facility":377155,
                "group":"education",
                "start":99,
                "duration":44,
                "time":143,
                "cum_utility":-18.6
            },
            {
                "acity":40,
                "facility":0,
                "group":"home",
                "start":144,
                "duration":84,
                "time":228,
                "cum_utility":-18.5
            },
            {
                "acity":32,
                "facility":377153,
                "group":"shop",
                "start":229,
                "duration":7,
                "time":236,
                "cum_utility":-28.9
            },
            {
                "acity":40,
                "facility":0,
                "group":"home",
                "start":237,
                "duration":49,
                "time":286,
                "cum_utility":-28.8
            },
            {
                "acity":41,
                "facility":0,
                "group":"home",
                "start":286,
                "duration":2,
                "time":288,
                "cum_utility":-28.8
            }
        ]
    },
    {
        "id":6633687,
        "execution_time":0.3,
        "DSSR_iterations":2,
        "utility":-36.254,
        "daily_schedule":[
            {
                "acity":0,
                "facility":0,
                "group":"home",
                "start":0,
                "duration":1,
                "time":1,
                "cum_utility":0.0
            },
            {
                "acity":40,
                "facility":0,
                "group":"home",
                "start":1,
                "duration":92,
                "time":93,
                "cum_utility":0.0
            },
            {
                "acity":38,
                "facility":377155,
                "group":"education",
                "start":95,
                "duration":43,
                "time":138,
                "cum_utility":-18.5
            },
            {
                "acity":40,
                "facility":0,
                "group":"home",
                "start":140,
                "duration":3,
                "time":143,
                "cum_utility":-18.3
            },
            {
                "acity":20,
                "facility":375697,
                "group":"leisure",
                "start":145,
                "duration":4,
                "time":149,
                "cum_utility":-23.354
            },
            {
                "acity":39,
                "facility":83189,
                "group":"work",
                "start":149,
                "duration":33,
                "time":182,
                "cum_utility":-36.454
            },
            {
                "acity":40,
                "facility":0,
                "group":"home",
                "start":184,
                "duration":102,
                "time":286,
                "cum_utility":-36.254
            },
            {
                "acity":41,
                "facility":0,
                "group":"home",
                "start":286,
                "duration":2,
                "time":288,
                "cum_utility":-36.254
            }
        ]
    }
]